devin/__init__.py
devin/main.py
devin/submodule/__init__.py
devin/submodule/chrome_helper.py
devin/submodule/cloud_helper.py
devin/submodule/cluster_helper.py
devin/submodule/config_helper.py
devin/submodule/crawal_helper.py
devin/submodule/csv_helper.py
devin/submodule/date_helper.py
devin/submodule/dict_helper.py
devin/submodule/distance_helper.py
devin/submodule/email_helper.py
devin/submodule/excel_helper.py
devin/submodule/flask_helper.py
devin/submodule/gensim_helper.py
devin/submodule/html_helper.py
devin/submodule/http_helper.py
devin/submodule/image_helper.py
devin/submodule/lemmatizer_helper.py
devin/submodule/list_helper.py
devin/submodule/main.py
devin/submodule/nltk_helper.py
devin/submodule/pattern_helper.py
devin/submodule/plot_helper.py
devin/submodule/position_helper.py
devin/submodule/profile_helper.py
devin/submodule/segment_helper.py
devin/submodule/store_helper.py
devin/submodule/system_helper.py
devin/submodule/text_helper.py
devin/submodule/wave_helper.py
devin/submodule/web_helper.py
devin/submodule/word_frequency.py
devin/submodule/tests/__init__.py
devin/submodule/tests/test_example.py
devin/tests/__init__.py
devin/tests/test_main.py
devin-1.0.0.data/data/ReleaseNotes.md
devin-1.0.0.dist-info/DESCRIPTION.rst
devin-1.0.0.dist-info/METADATA
devin-1.0.0.dist-info/RECORD
devin-1.0.0.dist-info/WHEEL
devin-1.0.0.dist-info/metadata.json
devin-1.0.0.dist-info/top_level.txt
