Metadata-Version: 2.0
Name: devin
Version: 1.0.0
Summary: This package creates a framework for python packages to be built.
Home-page: https://github.com/wuhaifengdhu/pypi-starter
Author: Wu Haifeng
Author-email: wuhaifengdhu@163.com
License: UNKNOWN
Platform: UNKNOWN
Requires-Dist: requests
Requires-Dist: six (>=1.10.0)
